vito_download/__init__.py
vito_download/_version.py
vito_download/config.py
vito_download/convenience.py
vito_download/download.py
vito_download/extract.py
vito_download/query.py
vito_download/read.py
vito_download/to_netcdf.py
vito_download_test-0.1.dist-info/LICENSE
vito_download_test-0.1.dist-info/METADATA
vito_download_test-0.1.dist-info/WHEEL
vito_download_test-0.1.dist-info/top_level.txt
vito_download_test-0.1.dist-info/RECORD
